pyneatR/__init__.py
pyneatR/dates.py
pyneatR/numbers.py
pyneatR/strings.py
pyneatR/utils.py
pyneatr-0.1.1.dist-info/licenses/LICENSE
pyneatr-0.1.1.dist-info/METADATA
pyneatr-0.1.1.dist-info/WHEEL
pyneatr-0.1.1.dist-info/top_level.txt
pyneatr-0.1.1.dist-info/RECORD
