Metadata-Version: 2.4
Name: pyneatR
Version: 0.1.1
Summary: Neat formatting for numbers, dates, and strings using numpy.
Author-email: Shivaprakash Suresh <dswithai@gmail.com>
License: MIT
Project-URL: Homepage, https://github.com/dswithai/pyneatR
Classifier: Programming Language :: Python :: 3
Classifier: License :: OSI Approved :: MIT License
Classifier: Operating System :: OS Independent
Requires-Python: >=3.9
License-File: LICENSE
Requires-Dist: numpy>=1.21.0
Provides-Extra: dev
Requires-Dist: pytest; extra == "dev"
Requires-Dist: pandas; extra == "dev"
Requires-Dist: polars; extra == "dev"
Dynamic: license-file
